django_db_reconnect/__init__.py
django_mysql_reconnect/__init__.py
django_mysql_reconnect-0.0.1.dist-info/METADATA
django_mysql_reconnect-0.0.1.dist-info/WHEEL
django_mysql_reconnect-0.0.1.dist-info/top_level.txt
django_mysql_reconnect-0.0.1.dist-info/RECORD
